gen_dual-0.1.0.dist-info/licenses/LICENCE
generalized_dual/__init__.py
generalized_dual/core.py
generalized_dual/experimental.py
generalized_dual/functions.py
generalized_dual/utils.py
generalized_dual/__pycache__/__init__.cpython-312.pyc
generalized_dual/__pycache__/core.cpython-312.pyc
generalized_dual/__pycache__/experimental.cpython-312.pyc
generalized_dual/__pycache__/functions.cpython-312.pyc
generalized_dual/__pycache__/utils.cpython-312.pyc
gen_dual-0.1.0.dist-info/METADATA
gen_dual-0.1.0.dist-info/WHEEL
gen_dual-0.1.0.dist-info/top_level.txt
gen_dual-0.1.0.dist-info/RECORD
