Metadata-Version: 2.4
Name: gen_dual
Version: 0.1.0
Summary: An implementation of generalized dual numbers with support for arbitrary precision and vectorization.
Home-page: https://github.com/LukaLavs/Automatic-Differentiation
Author: Luka Lavš
Author-email: lavslukal@gmail.com
Keywords: automatic differentiation,generalized dual numbers,numpy,mpmath
Classifier: Programming Language :: Python :: 3
Classifier: License :: OSI Approved :: MIT License
Classifier: Operating System :: OS Independent
Requires-Python: >=3.7
License-File: LICENCE
Requires-Dist: numpy
Requires-Dist: mpmath
Dynamic: author
Dynamic: author-email
Dynamic: classifier
Dynamic: description
Dynamic: description-content-type
Dynamic: home-page
Dynamic: keywords
Dynamic: license-file
Dynamic: requires-dist
Dynamic: requires-python
Dynamic: summary
